darkoverlay/__init__.py
darkoverlay/darkoverlay.py
darkoverlay-0.0.2.dist-info/LICENSE
darkoverlay-0.0.2.dist-info/METADATA
darkoverlay-0.0.2.dist-info/WHEEL
darkoverlay-0.0.2.dist-info/top_level.txt
darkoverlay-0.0.2.dist-info/RECORD
